{
    "platforms": {
        "platform": [
            {
                "vendor": "fujitsu",
                "name": "T400",
                "product-ids": [
                    "1.1.2"
                ],
                "os-type": "FSS2 Linux",
                "software-flavor": "Linux",
                "software-version": "1.1.2",
                "module-list-file": {
                    "owner": "fujitsu",
                    "path": "vendor/fujitsu/FSS2-API-Yang/T400/1.1.2/yang/T400-1.1.2-capabilities.xml",
                    "type": "capabilities",
                    "repository": "yang.git"
                }
            }
        ]
    }
}
